django_graphql_ratelimit/__init__.py
django_graphql_ratelimit/middleware.py
django_graphql_ratelimit/ratelimit.py
django_graphql_ratelimit/tests.py
example/__init__.py
example/settings.py
example/urls.py
example/wsgi.py
django_graphql_ratelimit-1.0.2.dist-info/METADATA
django_graphql_ratelimit-1.0.2.dist-info/WHEEL
django_graphql_ratelimit-1.0.2.dist-info/top_level.txt
django_graphql_ratelimit-1.0.2.dist-info/RECORD
